Neis_API/__init__.py
Neis_API/exceptions.py
Neis_API/mealInfo.py
Neis_API/schoolInfo.py
Neis_API/schoolschedule.py
Neis_API-0.6.0.dist-info/LICENSE
Neis_API-0.6.0.dist-info/METADATA
Neis_API-0.6.0.dist-info/WHEEL
Neis_API-0.6.0.dist-info/top_level.txt
Neis_API-0.6.0.dist-info/RECORD
