Metadata-Version: 2.1
Name: Neis-API
Version: 0.6.0
Summary: 나이스 API를 활용할 수 있게 도와주는 파이썬 패키지 입니다
Home-page: https://github.com/Piop2/Neis_API
Author: PIO
Author-email: seungyounyou0220@gmail.com
License: MIT
Platform: UNKNOWN
Classifier: Programming Language :: Python :: 3
Classifier: License :: OSI Approved :: MIT License
Classifier: Operating System :: OS Independent
License-File: LICENSE
